{
  "flags": {},
  "shapes": [
    {
      "label": "3",
      "line_color": null,
      "fill_color": null,
      "points": [
        [
          447,
          225
        ],
        [
          443,
          247
        ],
        [
          473,
          247
        ],
        [
          504,
          256
        ],
        [
          530,
          264
        ],
        [
          557,
          268
        ],
        [
          535,
          260
        ],
        [
          507,
          249
        ],
        [
          483,
          241
        ]
      ]
    },
    {
      "label": "2",
      "line_color": null,
      "fill_color": null,
      "points": [
        [
          453,
          56
        ],
        [
          462,
          38
        ],
        [
          491,
          59
        ],
        [
          522,
          73
        ],
        [
          559,
          93
        ],
        [
          483,
          63
        ]
      ]
    },
    {
      "label": "4",
      "line_color": null,
      "fill_color": null,
      "points": [
        [
          479,
          77
        ],
        [
          478,
          101
        ],
        [
          443,
          91
        ],
        [
          404,
          86
        ],
        [
          372,
          77
        ],
        [
          405,
          79
        ],
        [
          443,
          83
        ]
      ]
    },
    {
      "label": "1",
      "line_color": null,
      "fill_color": null,
      "points": [
        [
          711,
          402
        ],
        [
          693,
          408
        ],
        [
          682,
          370
        ],
        [
          672,
          340
        ],
        [
          681,
          305
        ],
        [
          680,
          338
        ],
        [
          688,
          358
        ]
      ]
    }
  ],
  "lineColor": [
    0,
    255,
    0,
    128
  ],
  "fillColor": [
    255,
    0,
    0,
    128
  ],
  "imagePath": "..\\img158.jpg",
  "imageData": null
}