{
  "flags": {},
  "shapes": [
    {
      "label": "1",
      "line_color": null,
      "fill_color": null,
      "points": [
        [
          191,
          137
        ],
        [
          188,
          154
        ],
        [
          302,
          170
        ]
      ]
    },
    {
      "label": "2",
      "line_color": null,
      "fill_color": null,
      "points": [
        [
          588,
          226
        ],
        [
          575,
          240
        ],
        [
          494,
          158
        ]
      ]
    },
    {
      "label": "3",
      "line_color": null,
      "fill_color": null,
      "points": [
        [
          377,
          626
        ],
        [
          379,
          643
        ],
        [
          341,
          640
        ],
        [
          320,
          631
        ],
        [
          304,
          619
        ],
        [
          280,
          607
        ],
        [
          298,
          606
        ],
        [
          322,
          624
        ],
        [
          341,
          634
        ],
        [
          362,
          630
        ]
      ]
    },
    {
      "label": "4",
      "line_color": null,
      "fill_color": null,
      "points": [
        [
          282,
          545
        ],
        [
          299,
          546
        ],
        [
          287,
          577
        ],
        [
          273,
          601
        ],
        [
          263,
          617
        ],
        [
          266,
          627
        ],
        [
          277,
          635
        ],
        [
          286,
          638
        ],
        [
          267,
          637
        ],
        [
          257,
          627
        ],
        [
          257,
          612
        ],
        [
          266,
          597
        ],
        [
          273,
          581
        ],
        [
          281,
          559
        ]
      ]
    }
  ],
  "lineColor": [
    0,
    255,
    0,
    128
  ],
  "fillColor": [
    255,
    0,
    0,
    128
  ],
  "imagePath": "..\\img44.jpg",
  "imageData": null
}