{
  "flags": {},
  "shapes": [
    {
      "label": "1",
      "line_color": null,
      "fill_color": null,
      "points": [
        [
          127,
          378
        ],
        [
          115,
          369
        ],
        [
          138,
          338
        ],
        [
          155,
          314
        ],
        [
          176,
          284
        ],
        [
          171,
          303
        ],
        [
          142,
          346
        ]
      ]
    },
    {
      "label": "4",
      "line_color": null,
      "fill_color": null,
      "points": [
        [
          352,
          316
        ],
        [
          369,
          323
        ],
        [
          323,
          431
        ]
      ]
    },
    {
      "label": "2",
      "line_color": null,
      "fill_color": null,
      "points": [
        [
          323,
          402
        ],
        [
          316,
          418
        ],
        [
          341,
          429
        ],
        [
          355,
          452
        ],
        [
          364,
          466
        ],
        [
          380,
          479
        ],
        [
          400,
          477
        ],
        [
          413,
          463
        ],
        [
          386,
          470
        ],
        [
          375,
          464
        ],
        [
          364,
          448
        ],
        [
          357,
          429
        ],
        [
          344,
          411
        ]
      ]
    },
    {
      "label": "3",
      "line_color": null,
      "fill_color": null,
      "points": [
        [
          469,
          609
        ],
        [
          452,
          616
        ],
        [
          426,
          641
        ],
        [
          391,
          645
        ],
        [
          378,
          617
        ],
        [
          398,
          634
        ],
        [
          416,
          634
        ],
        [
          445,
          600
        ],
        [
          468,
          592
        ]
      ]
    }
  ],
  "lineColor": [
    0,
    255,
    0,
    128
  ],
  "fillColor": [
    255,
    0,
    0,
    128
  ],
  "imagePath": "..\\img102.jpg",
  "imageData": null
}